{"MI/y5vTS/oaV3mVfdLhhYQ==":"mbr.jpg","RySyrkUrrPZPhzdrNWLxhg==":"mbr.jpeg","IedBUMFPy/wdQmKABiOf4g==":"mbr-1.jpg","X30aVRBEqsZY/bFEWmkiVg==":"mbr-2.jpg","YNiXBWgwNOjqA22Dmwqb5g==":"mbr-3.jpg","DrFPsfmeg5oSTFbYnhLeYw==":"mbr-4.jpg","6OY4DwgD2obALVw0F7NFIw==":"mbr-5.jpg","uEGJd4PrLTvFpgfDvYs4Lg==":"mbr-6.jpg","XRDdhODpZEaMtrsqfQDByg==":"mbr-7.jpg","+CFTCwDQuqe5qZvoVm36lQ==":"mbr-8.jpg","3ut2ml05952YX6wgEz26Cg==":"logoblancocfa-96x95.png","u4P8H54gA+o2eXnK2UshqA==":"if_14-1720385-97x97.png","VkXqHG/zMz4cszzgkeaw4Q==":"logoblanco-96x83.png","VBdgyurx8zmZq85SAn0Lpg==":"persp_p2-2000x1363.png","CTspEeRqj5HMDMpLJvEX4A==":"persp_p2-1-2000x1363.png","82XuKlksTusPlMl9IVIsTw==":"logo1-128x97.png","fF+q/JJ5k49H3cnNzyGAug==":"logo1-431x327.png","ihF8MIQd7EKFr7AXC73EJg==":"logo1-1-431x327.png","niPN36wIA7WE8OTyZ6Hj0Q==":"logo1-2-431x327.png","KlLmKBp8VAIpK9R4YaPo8g==":"logo1-3-431x327.png","zB62jwXfHvupAby5tJ73jA==":"logo%20naranja%2080-344x261.png","WLoAYViNagVuusLYQ0HRiw==":"logo%20naranja%2080b-390x282.png","wnXIAUXWYE3R/NaKUJmxRQ==":"logo%20naranja%2080b_text-390x282.png","abAi0XFsg7Z4qF8l8H7nnQ==":"logo%20naranja%2080b_text%20b-559x357.png","b3/Jb1R3qER1eIshvw1myQ==":"11032021_7080%20oakland_det-600x615.png","amxfB40R72mEXGng8tMRQw==":"01_frente_t1_c-600x419.jpg","wxaZ4rAgHVRR/7Z/QkPywA==":"vermont%20image3-600x338.png","veVtDu5y2yzchpZIstCFpA==":"vermont%20image3-600x338.png","DhRRZrDNfZpoUlEV1yddgQ==":"vermont%20sections-578x585.jpg","z+wyvPVkJ7//0lQVIgIzwQ==":"vermont%20sections-578x585.jpeg","0BjJjwLxP8FdiqmSsKzK1Q==":"vermont%20sections-578x585.jpeg","4FFu5isqU8CqZ9yU3ZDT6g==":"vermont%20sections-578x585.jpeg","hBpBYOEuiyHacYuPpiRhYw==":"sections%20inverted-534x541.jpg","g5xBmaYw2dxk01sDu2LE6w==":"details%20inverted-600x615.png"}